{
  "fetched_at": "2026-01-17T09:22:30.189114+00:00",
  "tiers": [
    1
  ],
  "stats": {
    "total_sources": 6,
    "successful": 3,
    "failed": 3,
    "total_items": 28,
    "new_items": 5
  },
  "new_items_count": 5,
  "items": [
    {
      "title": "CAT has jurisdiction to decide disputes relating to recruitment process of armed forces: Delhi High Court",
      "url": "https://www.barandbench.com/news/cat-has-jurisdiction-to-decide-disputes-relating-to-recruitment-process-of-armed-forces-delhi-high-court",
      "published": "2026-01-17T08:40:44.726Z",
      "snippet": "",
      "focus_areas": [
        "all"
      ],
      "source_id": "barandbench",
      "source_name": "Bar & Bench",
      "method": "rss"
    },
    {
      "title": "Legal Notes by Arvind Datar: Article 21 and the haunting words of Vivian Bose",
      "url": "https://www.barandbench.com/columns/legal-notes-by-arvind-datar-article-21-and-the-haunting-words-of-vivian-bose",
      "published": "2026-01-17T06:58:54.668Z",
      "snippet": "",
      "focus_areas": [
        "all"
      ],
      "source_id": "barandbench",
      "source_name": "Bar & Bench",
      "method": "rss"
    },
    {
      "title": "Who will the Tiger really bite?",
      "url": "https://www.barandbench.com/columns/who-will-the-tiger-really-bite",
      "published": "2026-01-17T06:19:00.551Z",
      "snippet": "",
      "focus_areas": [
        "all"
      ],
      "source_id": "barandbench",
      "source_name": "Bar & Bench",
      "method": "rss"
    },
    {
      "title": "Even if Justice Yashwant Varma is acquitted, nobody will believe he is an honest judge: Mukul Rohatgi on media trials",
      "url": "https://www.barandbench.com/news/even-if-justice-yashwant-varma-is-acquitted-nobody-will-believe-he-is-an-honest-judge-mukul-rohatgi-on-media-trials",
      "published": "2026-01-17T06:02:31.467Z",
      "snippet": "",
      "focus_areas": [
        "all"
      ],
      "source_id": "barandbench",
      "source_name": "Bar & Bench",
      "method": "rss"
    },
    {
      "title": "Supreme Court seeks Centre's response to plea seeking constitution of Arbitration Council of India",
      "url": "https://www.barandbench.com/news/litigation/supreme-court-seeks-centres-response-to-plea-seeking-constitution-of-arbitration-council-of-india",
      "published": "2026-01-17T04:37:00.672Z",
      "snippet": "",
      "focus_areas": [
        "all"
      ],
      "source_id": "barandbench",
      "source_name": "Bar & Bench",
      "method": "rss"
    }
  ],
  "page_changes": [
    {
      "source_id": "trai_main",
      "source_name": "TRAI",
      "section": "Consultation Papers",
      "url": "https://www.trai.gov.in/release-publication/consultation",
      "change_detected": true,
      "notable_links": [
        {
          "text": "LIST VIEW",
          "url": "https://www.trai.gov.in/release-publication/consultation#table-view"
        },
        {
          "text": "GRID VIEW",
          "url": "https://www.trai.gov.in/release-publication/consultation#grid-view"
        },
        {
          "text": "Download(25.89 MB)",
          "url": "https://www.trai.gov.in/sites/default/files/2025-11/CP_10112025.pdf"
        },
        {
          "text": "Download(464.49 KB)",
          "url": "https://www.trai.gov.in/sites/default/files/2025-12/PR_No.146of2025_0.pdf"
        },
        {
          "text": "Add/View Comments",
          "url": "https://www.trai.gov.in/consultation-paper-review-existing-trai-regulations-interconnection-matters"
        },
        {
          "text": "Download(160.51 KB)",
          "url": "https://www.trai.gov.in/sites/default/files/2025-10/Draft_Tariff_16102025.pdf"
        },
        {
          "text": "Download(841.33 KB)",
          "url": "https://www.trai.gov.in/sites/default/files/2025-10/PR_No.126of2025_0.pdf"
        },
        {
          "text": "Add/View Comments",
          "url": "https://www.trai.gov.in/draft-telecommunication-tariff-seventy-second-amendment-order-2025"
        },
        {
          "text": "Download(142.27 KB)",
          "url": "https://www.trai.gov.in/sites/default/files/2025-10/Draft_ASR_Regulation_16102025.pdf"
        },
        {
          "text": "Download(841.33 KB)",
          "url": "https://www.trai.gov.in/sites/default/files/2025-10/PR_No.126of2025_1.pdf"
        },
        {
          "text": "Add/View Comments",
          "url": "https://www.trai.gov.in/reporting-system-accounting-separation-amendment-regulations-2025"
        },
        {
          "text": "Download(16.41 MB)",
          "url": "https://www.trai.gov.in/sites/default/files/2025-09/CP_30092025.pdf"
        },
        {
          "text": "Download(477.77 KB)",
          "url": "https://www.trai.gov.in/sites/default/files/2025-10/PR_No.119of2025_0.pdf"
        },
        {
          "text": "Add/View Comments",
          "url": "https://www.trai.gov.in/consultation-paper-auction-radio-frequency-spectrum-frequency-bands-identified-international-mobile"
        },
        {
          "text": "Download(491.41 KB)",
          "url": "https://www.trai.gov.in/sites/default/files/2025-09/Draft_Regulation_22092025_0.pdf"
        },
        {
          "text": "Download(196.96 KB)",
          "url": "https://www.trai.gov.in/sites/default/files/2025-10/PR_No._105_of_2025.pdf_0.pdf"
        },
        {
          "text": "Add/View Comments",
          "url": "https://www.trai.gov.in/draft-telecommunication-broadcasting-and-cable-services-interconnection-addressable-systems-seventh"
        },
        {
          "text": "Download(7.17 MB)",
          "url": "https://www.trai.gov.in/sites/default/files/2025-07/CP_04072025.pdf"
        },
        {
          "text": "Add/View Comments",
          "url": "https://www.trai.gov.in/consultation-paper-regulatory-framework-sale-foreign-telecom-service-providers-simesim-cards-use"
        }
      ],
      "last_checked": "2026-01-17T09:22:45.611854+00:00"
    }
  ],
  "websearch_pending": [
    "egazette_india",
    "supreme_court",
    "pib_meity",
    "delhi_hc",
    "ftc_tech",
    "nlsiu_blog"
  ],
  "page_monitor_stats": {
    "total_pages": 22,
    "successful": 17,
    "failed": 5,
    "changes_detected": 1
  }
}